xfds/__init__.py
xfds/_render.py
xfds/_reset.py
xfds/_run.py
xfds/_stop.py
xfds/cli.py
xfds/config.py
xfds/core.py
xfds/errors.py
xfds/filters.py
xfds/log.py
xfds/units.py
xfds-0.3.0.dist-info/entry_points.txt
xfds-0.3.0.dist-info/LICENSE
xfds-0.3.0.dist-info/WHEEL
xfds-0.3.0.dist-info/METADATA
xfds-0.3.0.dist-info/RECORD
