Metadata-Version: 2.1
Name: xfds
Version: 0.3.0
Summary: Utility for managing FDS models
Home-page: https://xfds.pbd.tools
License: MIT
Author: Brian Cohan
Author-email: briancohan@pbd.tools
Requires-Python: >=3.8,<4.0
Classifier: Development Status :: 3 - Alpha
Classifier: Environment :: Console
Classifier: Intended Audience :: End Users/Desktop
Classifier: Intended Audience :: Science/Research
Classifier: License :: OSI Approved :: MIT License
Classifier: Natural Language :: English
Classifier: Programming Language :: Python :: 3
Classifier: Programming Language :: Python :: 3.10
Classifier: Programming Language :: Python :: 3.8
Classifier: Programming Language :: Python :: 3.9
Classifier: Topic :: Scientific/Engineering
Requires-Dist: Jinja2 (>=3.1.1,<4.0.0)
Requires-Dist: Markdown (>=3.3.6,<4.0.0)
Requires-Dist: Pint (>=0.19.2,<0.20.0)
Requires-Dist: PyYAML (>=6.0,<7.0)
Requires-Dist: numpy (>=1.23.1,<2.0.0)
Requires-Dist: pandas (>=1.4.3,<2.0.0)
Requires-Dist: toml (>=0.10.2,<0.11.0)
Requires-Dist: typer (>=0.4.0,<0.5.0)
Project-URL: Documentation, https://xfds.pbd.tools
Project-URL: Repository, https://github.com/pbdtools/xfds
